message_on_change/__init__.py
message_on_change/cli.py
message_on_change/fetch_logic.py
message_on_change/gui.py
message_on_change/guicontroll.py
message_on_change/status.py
message_on_change-0.1.0.dist-info/METADATA
message_on_change-0.1.0.dist-info/WHEEL
message_on_change-0.1.0.dist-info/entry_points.txt
message_on_change-0.1.0.dist-info/top_level.txt
message_on_change-0.1.0.dist-info/RECORD
