Metadata-Version: 2.1
Name: message-on-change
Version: 0.1.0
Summary: message_on_change
Author: Rūdolfs Driķis
Author-email: drikisr@gmail.com
Keywords: python,message_on_change,pyside6
Classifier: Development Status :: 3 - Alpha
Classifier: Intended Audience :: Education
Classifier: Programming Language :: Python :: 2
Classifier: Programming Language :: Python :: 3
Classifier: Operating System :: MacOS :: MacOS X
Classifier: Operating System :: Microsoft :: Windows
Requires-Dist: requests
Requires-Dist: playsound
Requires-Dist: pyside6
